// converted by version 1.3
// on Wed Apr 26 12:34:06 CEST 2017

.package fr/unilim {
	.aid 0x1:0x2:0x3:0x4:0x5:0x6:0x7:0x8;
	.version 1.0;

	.imports {
		0xA0:0x0:0x0:0x0:0x62:0x1:0x1 1.2;		//javacard/framework
		0xA0:0x0:0x0:0x0:0x62:0x0:0x1 1.0;		//java/lang
	}

	.applet {
		0x1:0x2:0x3:0x4:0x5:0x6:0x7:0x8:0x0:0x0 PorteMonnaie;
	}

	.constantPool {
		// 0
		instanceFieldRef short PorteMonnaie/balance;
		// 1
		staticMethodRef 0.3.0()V;		// javacard/framework/Applet.<init>()V
		// 2
		virtualMethodRef 0.3.1()V;		// register()V
		// 3
		classRef PorteMonnaie;
		// 4
		staticMethodRef PorteMonnaie/<init>()V;
		// 5
		staticMethodRef PorteMonnaie/$jacacocoEnd(Ljavacard/framework/APDU;)Z;
			.descriptor	Ljavacard/framework/APDU;	0.10;

		// 6
		virtualMethodRef 0.10.1()[B;		// getBuffer()[B
		// 7
		staticMethodRef 0.7.1(S)V;		// javacard/framework/ISOException.throwIt(S)V
		// 8
		virtualMethodRef 0.10.6()S;		// setIncomingAndReceive()S
		// 9
		staticMethodRef PorteMonnaie/$jacacocoInit()[B;
		// 10
		staticMethodRef 0.16.6([BSS)S;		// javacard/framework/Util.setShort([BSS)S
		// 11
		virtualMethodRef 0.10.7()S;		// setOutgoing()S
		// 12
		virtualMethodRef 0.10.8(SS)V;		// setOutgoingAndSend(SS)V
		// 13
		staticMethodRef 0.16.4([BS)S;		// javacard/framework/Util.getShort([BS)S
		// 14
		staticFieldRef byte[] PorteMonnaie/$jacacocoData;
		// 15
		staticMethodRef 0.16.2([BS[BSS)S;		// javacard/framework/Util.arrayCopyNonAtomic([BS[BSS)S
	}

	.class public PorteMonnaie 0 extends 0.3 {		// extends javacard/framework/Applet

		.fields {
			private short balance 0;		// S
			private static byte[] $jacacocoData;		// [B
		}

		.publicMethodTable 7 {
			equals(Ljava/lang/Object;)Z;
			register()V;
			register([BSB)V;
			selectingApplet()Z;
			deselect()V;
			getShareableInterfaceObject(Ljavacard/framework/AID;B)Ljavacard/framework/Shareable;;
			select()Z;
			process(Ljavacard/framework/APDU;)V;
		}

		.packageMethodTable 0 {
		}

		.method public <init>()V 0 {
			.stack 3;
			.locals 1;

				L0:	invokestatic 9;		// fr/unilim/PorteMonnaie.$jacacocoInit()[B
					astore_1;
					aload_0;
					invokespecial 1;		// javacard/framework/Applet.<init>()V
					aload_1;
					sconst_0;
					sconst_1;
					bastore;
					aload_0;
					invokevirtual 2;		// register()V
					aload_1;
					sconst_1;
					sconst_1;
					bastore;
					return;
		}

		.method public static install([BSB)V 1 {
			.stack 3;
			.locals 1;

				L0:	invokestatic 9;		// fr/unilim/PorteMonnaie.$jacacocoInit()[B
					astore_3;
					new 3;		// fr/unilim/PorteMonnaie
					invokespecial 4;		// fr/unilim/PorteMonnaie.<init>()V
					aload_3;
					sconst_2;
					sconst_1;
					bastore;
					return;
		}

		.method public process(Ljavacard/framework/APDU;)V 7 {
			.stack 4;
			.locals 5;

			.descriptor	Ljavacard/framework/APDU;	0.10;

				L0:	invokestatic 9;		// fr/unilim/PorteMonnaie.$jacacocoInit()[B
					astore_2;
					aload_1;
					invokestatic 5;		// fr/unilim/PorteMonnaie.$jacacocoEnd(Ljavacard/framework/APDU;)Z
					ifeq L2;
				L1:	return;
				L2:	aload_1;
					invokevirtual 6;		// getBuffer()[B
					astore_3;
					aload_3;
					sconst_0;
					baload;
					bspush -128;
					if_scmpne L4;
				L3:	aload_2;
					sconst_3;
					sconst_1;
					bastore;
					goto L5;
				L4:	aload_2;
					sconst_4;
					sconst_1;
					bastore;
					sspush 28160;
					aload_2;
					sconst_5;
					sconst_1;
					bastore;
					invokestatic 7;		// javacard/framework/ISOException.throwIt(S)V
				L5:	aload_3;
					sconst_1;
					baload;
					stableswitch L42 52 56 L6 L42 L18 L42 L30;
				L6:	aload_1;
					invokevirtual 8;		// setIncomingAndReceive()S
					sstore 4;
					sload 4;
					ifne L8;
				L7:	aload_2;
					bspush 6;
					sconst_1;
					bastore;
					goto L9;
				L8:	aload_2;
					bspush 7;
					sconst_1;
					bastore;
					sspush 26368;
					aload_2;
					bspush 8;
					sconst_1;
					bastore;
					invokestatic 7;		// javacard/framework/ISOException.throwIt(S)V
				L9:	aload_3;
					sconst_2;
					baload;
					ifne L11;
				L10:	aload_2;
					bspush 9;
					sconst_1;
					bastore;
					goto L14;
				L11:	aload_3;
					sconst_3;
					baload;
					ifne L13;
				L12:	aload_2;
					bspush 10;
					sconst_1;
					bastore;
					goto L14;
				L13:	aload_2;
					bspush 11;
					sconst_1;
					bastore;
					sspush 27270;
					aload_2;
					bspush 12;
					sconst_1;
					bastore;
					invokestatic 7;		// javacard/framework/ISOException.throwIt(S)V
				L14:	aload_3;
					sconst_0;
					getfield_s_this 0;		// short fr/unilim/PorteMonnaie.balance
					invokestatic 10;		// javacard/framework/Util.setShort([BSS)S
					pop;
					aload_2;
					bspush 13;
					sconst_1;
					bastore;
					aload_1;
					invokevirtual 11;		// setOutgoing()S
					bspush 16;
					if_scmplt L16;
				L15:	aload_2;
					bspush 14;
					sconst_1;
					bastore;
					goto L17;
				L16:	sspush 26368;
					aload_2;
					bspush 15;
					sconst_1;
					bastore;
					invokestatic 7;		// javacard/framework/ISOException.throwIt(S)V
				L17:	aload_1;
					sconst_0;
					sconst_2;
					invokevirtual 12;		// setOutgoingAndSend(SS)V
					aload_2;
					bspush 16;
					sconst_1;
					bastore;
					return;
				L18:	aload_1;
					invokevirtual 8;		// setIncomingAndReceive()S
					sstore 4;
					sload 4;
					sconst_2;
					if_scmpne L20;
				L19:	aload_2;
					bspush 17;
					sconst_1;
					bastore;
					goto L21;
				L20:	aload_2;
					bspush 18;
					sconst_1;
					bastore;
					sspush 26368;
					aload_2;
					bspush 19;
					sconst_1;
					bastore;
					invokestatic 7;		// javacard/framework/ISOException.throwIt(S)V
				L21:	aload_3;
					sconst_5;
					invokestatic 13;		// javacard/framework/Util.getShort([BS)S
					sstore 5;
					aload_3;
					sconst_2;
					baload;
					ifne L23;
				L22:	aload_2;
					bspush 20;
					sconst_1;
					bastore;
					goto L26;
				L23:	aload_3;
					sconst_3;
					baload;
					ifne L25;
				L24:	aload_2;
					bspush 21;
					sconst_1;
					bastore;
					goto L26;
				L25:	aload_2;
					bspush 22;
					sconst_1;
					bastore;
					sspush 27270;
					aload_2;
					bspush 23;
					sconst_1;
					bastore;
					invokestatic 7;		// javacard/framework/ISOException.throwIt(S)V
				L26:	sload 5;
					ifeq L28;
				L27:	aload_2;
					bspush 24;
					sconst_1;
					bastore;
					goto L29;
				L28:	aload_2;
					bspush 25;
					sconst_1;
					bastore;
					sspush 27012;
					aload_2;
					bspush 26;
					sconst_1;
					bastore;
					invokestatic 7;		// javacard/framework/ISOException.throwIt(S)V
				L29:	aload_0;
					dup;
					getfield_s 0;		// short fr/unilim/PorteMonnaie.balance
					sload 5;
					sadd;
					putfield_s 0;		// short fr/unilim/PorteMonnaie.balance
					aload_2;
					bspush 27;
					sconst_1;
					bastore;
					return;
				L30:	aload_1;
					invokevirtual 8;		// setIncomingAndReceive()S
					sstore 4;
					sload 4;
					sconst_2;
					if_scmpne L32;
				L31:	aload_2;
					bspush 28;
					sconst_1;
					bastore;
					goto L33;
				L32:	aload_2;
					bspush 29;
					sconst_1;
					bastore;
					sspush 26368;
					aload_2;
					bspush 30;
					sconst_1;
					bastore;
					invokestatic 7;		// javacard/framework/ISOException.throwIt(S)V
				L33:	aload_3;
					sconst_5;
					invokestatic 13;		// javacard/framework/Util.getShort([BS)S
					sstore 6;
					aload_3;
					sconst_2;
					baload;
					ifne L35;
				L34:	aload_2;
					bspush 31;
					sconst_1;
					bastore;
					goto L38;
				L35:	aload_3;
					sconst_3;
					baload;
					ifne L37;
				L36:	aload_2;
					bspush 32;
					sconst_1;
					bastore;
					goto L38;
				L37:	aload_2;
					bspush 33;
					sconst_1;
					bastore;
					sspush 27270;
					aload_2;
					bspush 34;
					sconst_1;
					bastore;
					invokestatic 7;		// javacard/framework/ISOException.throwIt(S)V
				L38:	getfield_s_this 0;		// short fr/unilim/PorteMonnaie.balance
					sload 6;
					if_scmplt L40;
				L39:	aload_2;
					bspush 35;
					sconst_1;
					bastore;
					goto L41;
				L40:	aload_2;
					bspush 36;
					sconst_1;
					bastore;
					sspush 27014;
					aload_2;
					bspush 37;
					sconst_1;
					bastore;
					invokestatic 7;		// javacard/framework/ISOException.throwIt(S)V
				L41:	aload_0;
					dup;
					getfield_s 0;		// short fr/unilim/PorteMonnaie.balance
					sload 6;
					ssub;
					putfield_s 0;		// short fr/unilim/PorteMonnaie.balance
					aload_2;
					bspush 38;
					sconst_1;
					bastore;
					return;
				L42:	sspush 27904;
					aload_2;
					bspush 39;
					sconst_1;
					bastore;
					invokestatic 7;		// javacard/framework/ISOException.throwIt(S)V
					aload_2;
					bspush 40;
					sconst_1;
					bastore;
					return;
		}

		.method private static $jacacocoInit()[B {
			.stack 2;
			.locals 0;

				L0:	getstatic_a 14;		// reference fr/unilim/PorteMonnaie.$jacacocoData
					dup;
					ifnonnull L2;
				L1:	pop;
					sspush 41;
					newarray 11;
					dup;
					putstatic_a 14;		// reference fr/unilim/PorteMonnaie.$jacacocoData
				L2:	areturn;
		}

		.method private static $jacacocoEnd(Ljavacard/framework/APDU;)Z {
			.stack 5;
			.locals 3;

			.descriptor	Ljavacard/framework/APDU;	0.10;

				L0:	aload_0;
					invokevirtual 6;		// getBuffer()[B
					astore_1;
					aload_1;
					sconst_0;
					baload;
					bspush 16;
					if_scmpne L3;
				L1:	aload_1;
					sconst_1;
					baload;
					bspush 16;
					if_scmpne L3;
				L2:	aload_1;
					sconst_2;
					baload;
					sspush 127;
					smul;
					sstore_2;
					aload_1;
					sconst_3;
					baload;
					sstore_3;
					getstatic_a 14;		// reference fr/unilim/PorteMonnaie.$jacacocoData
					sload_2;
					aload_1;
					sconst_0;
					sload_3;
					invokestatic 15;		// javacard/framework/Util.arrayCopyNonAtomic([BS[BSS)S
					pop;
					aload_0;
					sconst_0;
					sload_3;
					invokevirtual 12;		// setOutgoingAndSend(SS)V
					sconst_1;
					sreturn;
				L3:	sconst_0;
					sreturn;
		}

	}

}
